README.md
setup.py
SolrClient/__init__.py
SolrClient/collections.py
SolrClient/exceptions.py
SolrClient/indexq.py
SolrClient/schema.py
SolrClient/solrclient.py
SolrClient/solrresp.py
SolrClient/zk.py
SolrClient.egg-info/PKG-INFO
SolrClient.egg-info/SOURCES.txt
SolrClient.egg-info/dependency_links.txt
SolrClient.egg-info/requires.txt
SolrClient.egg-info/top_level.txt
SolrClient/helpers/__init__.py
SolrClient/helpers/reindexer.py
SolrClient/routers/__init__.py
SolrClient/routers/aware.py
SolrClient/routers/base.py
SolrClient/routers/plain.py
SolrClient/routers/pymmh3.py
SolrClient/transport/__init__.py
SolrClient/transport/transportbase.py
SolrClient/transport/transportrequests.py
test/RandomTestData.py
test/__init__.py
test/quick.py
test/test_client.py
test/test_collections.py
test/test_config.py
test/test_indexq.py
test/test_reindexer.py
test/test_resp.py
test/test_schema.py
test/test_zk.py