Metadata-Version: 1.0
Name: SolrClient
Version: 0.3.0
Summary: Python based client for Solr. 
Home-page: https://github.com/moonlitesolutions/SolrClient
Author: Nick Vasilyev
Author-email: nick.vasilyev1@gmail.com
License: UNKNOWN
Platform: UNKNOWN
